sql2statsd.py
sql2statsd-0.0.1.dist-info/DESCRIPTION.rst
sql2statsd-0.0.1.dist-info/METADATA
sql2statsd-0.0.1.dist-info/RECORD
sql2statsd-0.0.1.dist-info/WHEEL
sql2statsd-0.0.1.dist-info/entry_points.txt
sql2statsd-0.0.1.dist-info/metadata.json
sql2statsd-0.0.1.dist-info/top_level.txt
