Metadata-Version: 2.0
Name: sql2statsd
Version: 0.0.1
Summary: CLI utility that queries SQL database and posts results to StatsD.
Home-page: https://github.com/Suenweek/sql2statsd
Author: Suenweek
Author-email: suenweek@protonmail.com
License: MIT
Platform: UNKNOWN
Requires-Dist: PyYAML
Requires-Dist: click
Requires-Dist: psycopg2
Requires-Dist: statsd
